Metadata-Version: 2.1
Name: lcwa
Version: 0.1.0
Summary: LCWA (Loss Curvature Weighted Averaging) implementation for PyTorch
Home-page: https://github.com/wangyunjeff/lcwa
Author: Your Name
Author-email: your.email@example.com
Classifier: Programming Language :: Python :: 3
Classifier: License :: OSI Approved :: MIT License
Classifier: Operating System :: OS Independent
Requires-Python: >=3.6
